markdownfeeds/Gatherer.py
markdownfeeds/MarkdownFile.py
markdownfeeds/__init__.py
markdownfeeds/Exceptions/__init__.py
markdownfeeds/Generators/__init__.py
markdownfeeds/Generators/Default/DefaultFeedGenerator.py
markdownfeeds/Generators/Default/Exceptions/__init__.py
markdownfeeds/Generators/Default/Models/Feed.py
markdownfeeds/Generators/Default/Models/FeedItem.py
markdownfeeds/Generators/Default/Models/__init__.py
markdownfeeds/Generators/Html/HtmlFeedGenerator.py
markdownfeeds/Generators/Html/template.html
markdownfeeds/Generators/Json/JsonFeedGenerator.py
markdownfeeds/Generators/Json/Models/Author.py
markdownfeeds/Generators/Json/Models/Hub.py
markdownfeeds/Generators/Json/Models/JsonFeed.py
markdownfeeds/Generators/Json/Models/JsonFeedItem.py
markdownfeeds/Generators/Json/Models/__init__.py
markdownfeeds-1.9.1.dist-info/LICENSE
markdownfeeds-1.9.1.dist-info/METADATA
markdownfeeds-1.9.1.dist-info/WHEEL
markdownfeeds-1.9.1.dist-info/top_level.txt
markdownfeeds-1.9.1.dist-info/RECORD
