Metadata-Version: 2.1
Name: markdownfeeds
Version: 1.9.1
Summary: Small library that can generated paged feeds (json, html, etc) based on a collection of markdown files.
Author-email: Scott Straughan <dev@strong.scot>
Project-URL: Homepage, https://github.com/scottstraughan/markdowntofeed
Project-URL: Issues, https://github.com/scottstraughan/markdowntofeed/issues
Classifier: Programming Language :: Python :: 3
Classifier: License :: OSI Approved :: MIT License
Classifier: Operating System :: OS Independent
Requires-Python: >=3.11.0
License-File: LICENSE
Requires-Dist: pyyaml
Requires-Dist: python-dateutil
Requires-Dist: markdown
Requires-Dist: html2text
Requires-Dist: chevron
Requires-Dist: requests
